emptyfile/__init__.py
emptyfile/__main__.py
emptyfile/remover.py
tests/__init__.py
tests/requirements.txt
tests/test_remover.py
emptyfile-0.1.1.dist-info/LICENSE
emptyfile-0.1.1.dist-info/METADATA
emptyfile-0.1.1.dist-info/WHEEL
emptyfile-0.1.1.dist-info/entry_points.txt
emptyfile-0.1.1.dist-info/top_level.txt
emptyfile-0.1.1.dist-info/RECORD
