Metadata-Version: 2.1
Name: emptyfile
Version: 0.1.1
Summary: empty file/folder remover.
Home-page: https://github.com/alexpdev/emptyfile
Author: alexpdev
Author-email: alexpdev@pm.me
License: Apache License
Keywords: cli,filesystem
Classifier: Development Status :: 3 - Alpha
Classifier: Programming Language :: Python :: 3
Classifier: Environment :: Console
Classifier: License :: OSI Approved :: Apache Software License
Classifier: Operating System :: OS Independent
Classifier: Topic :: Utilities
Classifier: Programming Language :: Python :: 3.5
Classifier: Programming Language :: Python :: 3.6
Classifier: Programming Language :: Python :: 3.7
Classifier: Programming Language :: Python :: 3.8
Classifier: Programming Language :: Python :: 3.9
Classifier: Programming Language :: Python :: 3.10
License-File: LICENSE
